nlp_cache/__init__.py
nlp_cache/nlp_cache.py
nlp_cache_sebastian_stigler-0.3.0.dist-info/LICENSE
nlp_cache_sebastian_stigler-0.3.0.dist-info/METADATA
nlp_cache_sebastian_stigler-0.3.0.dist-info/WHEEL
nlp_cache_sebastian_stigler-0.3.0.dist-info/top_level.txt
nlp_cache_sebastian_stigler-0.3.0.dist-info/RECORD
