Metadata-Version: 2.1
Name: nlp-cache-sebastian-stigler
Version: 0.3.0
Summary: A caching component for `Doc` classes in `spacy`.
Home-page: https://in-stigler.htw-aalen.de/gitea/bantel/nlp_cache
Author: Sebastian Stigler
Author-email: sebastian.stigler@hs-aalen.de
License: UNKNOWN
Platform: UNKNOWN
Classifier: Intended Audience :: Education
Classifier: Programming Language :: Python :: 3
Classifier: Programming Language :: Python :: 3.6
Classifier: Programming Language :: Python :: 3.7
Classifier: Programming Language :: Python :: 3.8
Classifier: Programming Language :: Python :: 3.9
Classifier: Programming Language :: Python :: 3.10
Classifier: License :: OSI Approved :: MIT License
Requires-Python: >=3.6
License-File: LICENSE
Requires-Dist: spacy (>=3.2.3)
